{
  "modules": {
    "byIdentifier": {
      "multi ../node_modules/next/dist/client/next": 0,
      "multi node_modules/next/dist/client/next": 0
    },
    "usedIds": {
      "0": 0
    }
  },
  "chunks": {
    "byName": {
      "commons": 0,
      "static/runtime/webpack.js": 1,
      "static/runtime/main.js": 2,
      "static\\KAkseRIcTm~z2uedP3xih\\pages\\_app.js": 3,
      "static\\KAkseRIcTm~z2uedP3xih\\pages\\_error.js": 4,
      "static\\KAkseRIcTm~z2uedP3xih\\pages\\cats.js": 5,
      "static\\KAkseRIcTm~z2uedP3xih\\pages\\cats\\_breed.js": 6,
      "static\\KAkseRIcTm~z2uedP3xih\\pages\\index.js": 7,
      "static\\Ri4oxoHeyIN4Zxrqog7qr\\pages\\_app.js": 8,
      "static\\Ri4oxoHeyIN4Zxrqog7qr\\pages\\_error.js": 9,
      "static\\Ri4oxoHeyIN4Zxrqog7qr\\pages\\cats.js": 10,
      "static\\Ri4oxoHeyIN4Zxrqog7qr\\pages\\cats\\_breed.js": 11,
      "static\\Ri4oxoHeyIN4Zxrqog7qr\\pages\\index.js": 12,
      "static\\eUFmynIoZMC9xxnD~gdL9\\pages\\_app.js": 3,
      "static\\eUFmynIoZMC9xxnD~gdL9\\pages\\_error.js": 4,
      "static\\eUFmynIoZMC9xxnD~gdL9\\pages\\cats.js": 5,
      "static\\eUFmynIoZMC9xxnD~gdL9\\pages\\cats\\_breed.js": 6,
      "static\\eUFmynIoZMC9xxnD~gdL9\\pages\\index.js": 7,
      "static\\1e0qz1GzVwOIvmxLW4UPL\\pages\\_app.js": 8,
      "static\\1e0qz1GzVwOIvmxLW4UPL\\pages\\_error.js": 9,
      "static\\1e0qz1GzVwOIvmxLW4UPL\\pages\\cats.js": 10,
      "static\\1e0qz1GzVwOIvmxLW4UPL\\pages\\cats\\_breed.js": 11,
      "static\\1e0qz1GzVwOIvmxLW4UPL\\pages\\index.js": 12,
      "static\\enxUFBENWsuTlBQzcnKdb\\pages\\_app.js": 3,
      "static\\enxUFBENWsuTlBQzcnKdb\\pages\\_error.js": 4,
      "static\\enxUFBENWsuTlBQzcnKdb\\pages\\cats.js": 5,
      "static\\enxUFBENWsuTlBQzcnKdb\\pages\\cats\\_breed.js": 6,
      "static\\enxUFBENWsuTlBQzcnKdb\\pages\\index.js": 7,
      "static\\kTSrN~uMZEnOtZ4nBtfgT\\pages\\_app.js": 8,
      "static\\kTSrN~uMZEnOtZ4nBtfgT\\pages\\_error.js": 9,
      "static\\kTSrN~uMZEnOtZ4nBtfgT\\pages\\cats.js": 10,
      "static\\kTSrN~uMZEnOtZ4nBtfgT\\pages\\cats\\_breed.js": 11,
      "static\\kTSrN~uMZEnOtZ4nBtfgT\\pages\\index.js": 12,
      "static\\f0eVwPjU2gA18Hw81q5mi\\pages\\_app.js": 3,
      "static\\f0eVwPjU2gA18Hw81q5mi\\pages\\_error.js": 4,
      "static\\f0eVwPjU2gA18Hw81q5mi\\pages\\cats.js": 5,
      "static\\f0eVwPjU2gA18Hw81q5mi\\pages\\cats\\_breed.js": 6,
      "static\\f0eVwPjU2gA18Hw81q5mi\\pages\\index.js": 7,
      "static\\jxickuC1dxtarsDNWI2TK\\pages\\_app.js": 8,
      "static\\jxickuC1dxtarsDNWI2TK\\pages\\_error.js": 9,
      "static\\jxickuC1dxtarsDNWI2TK\\pages\\cats.js": 10,
      "static\\jxickuC1dxtarsDNWI2TK\\pages\\cats\\_breed.js": 11,
      "static\\jxickuC1dxtarsDNWI2TK\\pages\\index.js": 12,
      "static\\AacmNSxtwGa8UsMlobioq\\pages\\_app.js": 3,
      "static\\AacmNSxtwGa8UsMlobioq\\pages\\_error.js": 4,
      "static\\AacmNSxtwGa8UsMlobioq\\pages\\cats.js": 5,
      "static\\AacmNSxtwGa8UsMlobioq\\pages\\cats\\_breed.js": 6,
      "static\\AacmNSxtwGa8UsMlobioq\\pages\\index.js": 7,
      "static\\qV7YVstgKCzYfAKUC7kL1\\pages\\_app.js": 8,
      "static\\qV7YVstgKCzYfAKUC7kL1\\pages\\_error.js": 9,
      "static\\qV7YVstgKCzYfAKUC7kL1\\pages\\cats.js": 10,
      "static\\qV7YVstgKCzYfAKUC7kL1\\pages\\cats\\_breed.js": 11,
      "static\\qV7YVstgKCzYfAKUC7kL1\\pages\\index.js": 12,
      "static\\eY7UZpNwoH9Mv3ane9aEf\\pages\\_app.js": 3,
      "static\\eY7UZpNwoH9Mv3ane9aEf\\pages\\_error.js": 4,
      "static\\eY7UZpNwoH9Mv3ane9aEf\\pages\\cats.js": 5,
      "static\\eY7UZpNwoH9Mv3ane9aEf\\pages\\cats\\_breed.js": 6,
      "static\\eY7UZpNwoH9Mv3ane9aEf\\pages\\index.js": 7,
      "static\\JoIJjnvvV~~1NorM8lges\\pages\\_app.js": 8,
      "static\\JoIJjnvvV~~1NorM8lges\\pages\\_error.js": 9,
      "static\\JoIJjnvvV~~1NorM8lges\\pages\\cats.js": 10,
      "static\\JoIJjnvvV~~1NorM8lges\\pages\\cats\\_breed.js": 11,
      "static\\JoIJjnvvV~~1NorM8lges\\pages\\index.js": 12,
      "static\\iEaSEZt8bdBDKTGVs5MHX\\pages\\_app.js": 3,
      "static\\iEaSEZt8bdBDKTGVs5MHX\\pages\\_error.js": 4,
      "static\\iEaSEZt8bdBDKTGVs5MHX\\pages\\cats.js": 5,
      "static\\iEaSEZt8bdBDKTGVs5MHX\\pages\\cats\\_breed.js": 6,
      "static\\iEaSEZt8bdBDKTGVs5MHX\\pages\\index.js": 7,
      "static\\5c_nXrAOZo9dOZfkDIiOf\\pages\\_app.js": 8,
      "static\\5c_nXrAOZo9dOZfkDIiOf\\pages\\_error.js": 9,
      "static\\5c_nXrAOZo9dOZfkDIiOf\\pages\\cats.js": 10,
      "static\\5c_nXrAOZo9dOZfkDIiOf\\pages\\cats\\_breed.js": 11,
      "static\\5c_nXrAOZo9dOZfkDIiOf\\pages\\index.js": 12
    },
    "bySource": {},
    "usedIds": [
      0,
      1,
      10,
      11,
      12,
      2,
      8,
      9
    ]
  }
}